keepassxc_proxy_client/__init__.py
keepassxc_proxy_client/__main__.py
keepassxc_proxy_client/protocol.py
keepassxc_proxy_client-0.1.7.dist-info/LICENSE
keepassxc_proxy_client-0.1.7.dist-info/METADATA
keepassxc_proxy_client-0.1.7.dist-info/WHEEL
keepassxc_proxy_client-0.1.7.dist-info/entry_points.txt
keepassxc_proxy_client-0.1.7.dist-info/top_level.txt
keepassxc_proxy_client-0.1.7.dist-info/zip-safe
keepassxc_proxy_client-0.1.7.dist-info/RECORD
