Metadata-Version: 2.1
Name: keepassxc-proxy-client
Version: 0.1.7
Summary: A CLI for keepassxc-proxy
Home-page: https://github.com/hargoniX/keepassxc-proxy-client
Author: Henrik Boeving
Author-email: hargonix@gmail.com
Project-URL: Issue tracker, https://github.com/hargoniX/keepassxc-proxy-client/issues
Project-URL: Changelog, https://github.com/hargoniX/keepassxc-proxy-client/blob/master/CHANGELOG.md
Classifier: Development Status :: 4 - Beta
Classifier: Environment :: Console
Classifier: Programming Language :: Python :: 3.6
Classifier: Programming Language :: Python :: 3.7
Classifier: Programming Language :: Python :: 3.8
Classifier: Intended Audience :: Developers
Classifier: Intended Audience :: System Administrators
Classifier: Intended Audience :: Information Technology
Classifier: Topic :: Software Development :: Libraries :: Python Modules
Classifier: Topic :: Software Development :: Libraries
Classifier: Topic :: System :: Systems Administration
Classifier: Topic :: System :: Networking
Classifier: Topic :: Utilities
License-File: LICENSE
Requires-Dist: pynacl
Requires-Dist: pywin32 ; sys_platform == "win32"
